allstarlink_keyed/__init__.py
allstarlink_keyed/main.py
allstarlink_keyed-0.1.4.dist-info/METADATA
allstarlink_keyed-0.1.4.dist-info/WHEEL
allstarlink_keyed-0.1.4.dist-info/entry_points.txt
allstarlink_keyed-0.1.4.dist-info/top_level.txt
allstarlink_keyed-0.1.4.dist-info/RECORD
